{
    "Ax": {
        "error": 1.4016068499565973e-07,
        "error_type": "SEM",
        "filter_outliers_dict": {
            "filter_outliers": false,
            "iterations": 1,
            "std_devs": 2
        },
        "fit": "average",
        "value": -2.0733681035307436e-06
    },
    "H2": {
        "error": 1.3544056840805576e-07,
        "error_type": "SEM",
        "filter_outliers_dict": {
            "filter_outliers": true,
            "iterations": 1,
            "std_devs": 2
        },
        "fit": "average",
        "value": -1.6426688939941656e-06
    },
    "H4": {
        "error": 8.747279621608941e-08,
        "error_type": "SEM",
        "filter_outliers_dict": {
            "filter_outliers": true,
            "iterations": 1,
            "std_devs": 2
        },
        "fit": "average",
        "value": -1.4085722244482759e-06
    },
    "L2": {
        "error": 1.5389837669072168e-07,
        "error_type": "SEM",
        "filter_outliers_dict": {
            "filter_outliers": true,
            "iterations": 1,
            "std_devs": 2
        },
        "fit": "average",
        "value": -2.9245038816428066e-06
    },
    "L4": {
        "error": 1.8153876125797617e-09,
        "error_type": "SEM",
        "filter_outliers_dict": {
            "filter_outliers": false,
            "iterations": 1,
            "std_devs": 2
        },
        "fit": "average",
        "value": 6.400000000000001e-09
    }
}